wannacri/__init__.py
wannacri/__main__.py
wannacri/codec.py
wannacri/wannacri.py
wannacri/usm/__init__.py
wannacri/usm/chunk.py
wannacri/usm/page.py
wannacri/usm/tools.py
wannacri/usm/types.py
wannacri/usm/usm.py
wannacri/usm/media/__init__.py
wannacri/usm/media/audio.py
wannacri/usm/media/protocols.py
wannacri/usm/media/tools.py
wannacri/usm/media/video.py
WannaCRI-0.3.0.dist-info/LICENCE
WannaCRI-0.3.0.dist-info/METADATA
WannaCRI-0.3.0.dist-info/WHEEL
WannaCRI-0.3.0.dist-info/entry_points.txt
WannaCRI-0.3.0.dist-info/top_level.txt
WannaCRI-0.3.0.dist-info/RECORD
