Metadata-Version: 2.1
Name: WannaCRI
Version: 0.3.0
Summary: Criware media formats library
Home-page: https://github.com/donmai-me/WannaCRI
Author: donmai
Classifier: Programming Language :: Python :: 3
Classifier: Programming Language :: Python :: 3.8
Classifier: License :: OSI Approved :: MIT License
Classifier: Operating System :: OS Independent
Classifier: Development Status :: 3 - Alpha
Classifier: Intended Audience :: Developers
Classifier: Topic :: Games/Entertainment
Requires-Python: ~=3.8
License-File: LICENCE
